roundrobin/__init__.py
roundrobin/basic_rr.py
roundrobin/smooth_rr.py
roundrobin/weighted_rr.py
roundrobin-0.0.1.dist-info/METADATA
roundrobin-0.0.1.dist-info/WHEEL
roundrobin-0.0.1.dist-info/top_level.txt
roundrobin-0.0.1.dist-info/RECORD
