Metadata-Version: 2.1
Name: roundrobin
Version: 0.0.1
Summary: Collection of roundrobin utilities
Home-page: https://github.com/linnik/roundrobin
Author: Vyacheslav Linnik
Author-email: hello@slavalinnik.com
License: MIT
Platform: UNKNOWN
Classifier: License :: OSI Approved :: MIT License
Classifier: Programming Language :: Python :: 3
Classifier: Programming Language :: Python :: 3.5
